ucaptcha/__init__.py
ucaptcha/anticaptcha.py
ucaptcha/auth.py
ucaptcha/capmonster.py
ucaptcha/exceptions.py
ucaptcha/humancaptcha.py
ucaptcha/logger.py
ucaptcha/nocaptchaai.py
ucaptcha/nopecha.py
ucaptcha/proxies.py
ucaptcha/py.typed
ucaptcha/solver.py
ucaptcha/twocaptcha.py
ucaptcha-1.1.4.dist-info/LICENSE
ucaptcha-1.1.4.dist-info/METADATA
ucaptcha-1.1.4.dist-info/WHEEL
ucaptcha-1.1.4.dist-info/top_level.txt
ucaptcha-1.1.4.dist-info/RECORD
