Metadata-Version: 2.1
Name: ucaptcha
Version: 1.1.4
Summary: Universal captcha solving python module
Author-email: Pradish Bijukchhe <pradish@sandbox.com.np>
License: Copyright (c) 2024 Pradish Bijukchhe
Project-URL: Homepage, https://github.com/sandbox-pokhara/ucaptcha
Project-URL: Issues, https://github.com/sandbox-pokhara/ucaptcha/issues
Classifier: Programming Language :: Python :: 3
Requires-Python: >=3
License-File: LICENSE
Requires-Dist: httpx
